Metadata-Version: 2.1
Name: ta-cn
Version: 0.5.2
Summary: Technical Analysis Indicators
Home-page: https://github.com/wukan1986/ta_cn
Author: wukan
Author-email: wu-kan@163.com
License: UNKNOWN
Platform: UNKNOWN
Classifier: Programming Language :: Python :: 3
Classifier: License :: OSI Approved :: MIT License
Classifier: Operating System :: OS Independent
Classifier: Intended Audience :: Developers
Requires-Python: >=3.7
License-File: LICENSE
Requires-Dist: numpy
Requires-Dist: loguru
Provides-Extra: cn
Requires-Dist: numpy (>=1.20.0) ; extra == 'cn'
Requires-Dist: pandas ; extra == 'cn'
Requires-Dist: bottleneck ; extra == 'cn'
Requires-Dist: numba ; extra == 'cn'
Provides-Extra: parallel
Requires-Dist: parmap ; extra == 'parallel'
Provides-Extra: talib
Requires-Dist: TA-Lib (>=0.4.19) ; extra == 'talib'
